<?xml version="1.0" encoding="utf-8"?>
<Deployment xmlns="http://schemas.microsoft.com/windowsphone/2012/deployment" AppPlatformVersion="8.0">
  <DefaultLanguage xmlns="" code="en-US" />
  <App xmlns="" ProductID="{099b9638-b3e5-4242-94f9-a8d227ea0cc2}" Title="Brac Bank Locator" RuntimeType="Silverlight" Version="1.0.0.0" Genre="apps.normal" Author="BracBankLocator author" Description="Sample description" Publisher="BracBankLocator" PublisherID="{1b88654a-0deb-431e-ad79-2f43550cd811}">
    <IconPath IsRelative="true" IsResource="false">ApplicationIcon.png</IconPath>
    <Capabilities>
      <Capability Name="ID_CAP_NETWORKING" />
      <Capability Name="ID_CAP_MEDIALIB_AUDIO" />
      <Capability Name="ID_CAP_MEDIALIB_PLAYBACK" />
      <Capability Name="ID_CAP_SENSORS" />
      <Capability Name="ID_CAP_WEBBROWSERCOMPONENT" />
      <Capability Name="ID_CAP_LOCATION" />
      <Capability Name="ID_CAP_MAP" />
    </Capabilities>
    <Tasks>
      <DefaultTask Name="_default" NavigationPage="SplashScreen.xaml" />
    </Tasks>
    <Tokens>
      <PrimaryToken TokenID="BracBankLocatorToken" TaskName="_default">
        <TemplateFlip>
          <SmallImageURI IsRelative="true" IsResource="false">FlipCycleTileSmall.png</SmallImageURI>
          <Count>0</Count>
          <BackgroundImageURI IsRelative="true" IsResource="false">FlipCycleTileMedium.png</BackgroundImageURI>
          <Title>Brac Bank Locator</Title>
          <BackContent>
          </BackContent>
          <BackBackgroundImageURI>
          </BackBackgroundImageURI>
          <BackTitle>
          </BackTitle>
          <LargeBackgroundImageURI IsRelative="true" IsResource="false">FlipCycleTileLarge.png</LargeBackgroundImageURI>
          <LargeBackContent />
          <LargeBackBackgroundImageURI IsRelative="true" IsResource="false">
          </LargeBackBackgroundImageURI>
          <DeviceLockImageURI>
          </DeviceLockImageURI>
          <HasLarge>True</HasLarge>
        </TemplateFlip>
      </PrimaryToken>
    </Tokens>
    <ScreenResolutions>
      <ScreenResolution Name="ID_RESOLUTION_WVGA" />
      <ScreenResolution Name="ID_RESOLUTION_WXGA" />
      <ScreenResolution Name="ID_RESOLUTION_HD720P" />
    </ScreenResolutions>
  </App>
</Deployment>